[
  {
    "type": "Liquor",
    "name": "Total Wine More",
    "lat": 27.958194,
    "long": -82.506311,
    "gmapsCategory": "Liquor store"
  },
  {
    "type": "Liquor",
    "name": "Redneck Wine Co",
    "lat": 27.915882,
    "long": -82.49435,
    "gmapsCategory": "Wine store"
  },
  {
    "type": "Liquor",
    "name": "ABC Fine Wine Spirits",
    "lat": 27.9450962,
    "long": -82.4920004,
    "gmapsCategory": "Liquor store"
  },
  {
    "type": "Liquor",
    "name": " th Street Cutrate Liquors",
    "lat": 27.9739383,
    "long": -82.4432589,
    "gmapsCategory": "Liquor store"
  },
  {
    "type": "Liquor",
    "name": "Luekens Wine Spirits",
    "lat": 27.9451417,
    "long": -82.5228903,
    "gmapsCategory": "Wine store"
  },
  {
    "type": "Liquor",
    "name": "Fine Wine Spirits Warehouse",
    "lat": 27.8940598,
    "long": -82.5120445,
    "gmapsCategory": "Liquor store"
  },
  {
    "type": "Liquor",
    "name": "Winn Dixie Wine Spirits",
    "lat": 27.9807866,
    "long": -82.4526277,
    "gmapsCategory": "Liquor store"
  },
  {
    "type": "Liquor",
    "name": "Goodtime Liquor Inc",
    "lat": 28.0015621,
    "long": -82.3929803,
    "gmapsCategory": "Liquor store"
  },
  {
    "type": "Liquor",
    "name": "Florida Avenue Liquors",
    "lat": 27.9710564,
    "long": -82.4592183,
    "gmapsCategory": "Liquor store"
  },
  {
    "type": "Liquor",
    "name": "Luekens Wine Spirits",
    "lat": 27.9473389,
    "long": -82.5059832,
    "gmapsCategory": "Wine store"
  },
  {
    "type": "Liquor",
    "name": "ABC Fine Wine Spirits",
    "lat": 27.8932394,
    "long": -82.4948816,
    "gmapsCategory": "Liquor store"
  },
  {
    "type": "Liquor",
    "name": "Super th Liquor Store",
    "lat": 27.9616836,
    "long": -82.4040699,
    "gmapsCategory": "Liquor store"
  },
  {
    "type": "Liquor",
    "name": "Liquor Depot Hillsborough",
    "lat": 27.9976619,
    "long": -82.5016015,
    "gmapsCategory": "Liquor store"
  },
  {
    "type": "Liquor",
    "name": "Lake Avenue Package",
    "lat": 27.9776656,
    "long": -82.4340862,
    "gmapsCategory": "Liquor store"
  },
  {
    "type": "Liquor",
    "name": "LATAM LIQUORS",
    "lat": 27.9668421,
    "long": -82.4850595,
    "gmapsCategory": "Liquor store"
  },
  {
    "type": "Liquor",
    "name": "Priced Rite Liquor, Wine More",
    "lat": 27.9573264,
    "long": -82.4806411,
    "gmapsCategory": "Liquor store"
  },
  {
    "type": "Liquor",
    "name": "Pauls liquor store",
    "lat": 27.9739386,
    "long": -82.4432733,
    "gmapsCategory": "Liquor store"
  },
  {
    "type": "Liquor",
    "name": "Duckweed Liquors Channelside",
    "lat": 27.948178,
    "long": -82.446583,
    "gmapsCategory": "Liquor store"
  },
  {
    "type": "Liquor",
    "name": "Bern s Fine Wines Spirits",
    "lat": 27.930693,
    "long": -82.4832998,
    "gmapsCategory": "Wine store"
  },
  {
    "type": "Liquor",
    "name": "Cheers Wine and Liquor",
    "lat": 27.9957461,
    "long": -82.4170166,
    "gmapsCategory": "Liquor store"
  },
  {
    "type": "Liquor",
    "name": "Bottlesmith",
    "lat": 27.947214,
    "long": -82.4766148,
    "gmapsCategory": "Liquor store"
  },
  {
    "type": "Liquor",
    "name": "Westshore Liquors and Cigars",
    "lat": 27.9099211,
    "long": -82.526443,
    "gmapsCategory": "Liquor store"
  },
  {
    "type": "Liquor",
    "name": "Warehouse Liquor Store and Bar",
    "lat": 27.8939618,
    "long": -82.5119927,
    "gmapsCategory": "Liquor store"
  },
  {
    "type": "Liquor",
    "name": "National Liquor Package Near Ybor City Casino",
    "lat": 27.9743824,
    "long": -82.4012692,
    "gmapsCategory": "Liquor store"
  },
  {
    "type": "Liquor",
    "name": "Publix Liquors at Dale Mabry Shopping Center",
    "lat": 27.9312065,
    "long": -82.5071667,
    "gmapsCategory": "Liquor store"
  },
  {
    "type": "Liquor",
    "name": "Soho Gourmet Fine Wine, Beer Smoke Shop",
    "lat": 27.9413867,
    "long": -82.4665389,
    "gmapsCategory": "Convenience store"
  },
  {
    "type": "Liquor",
    "name": "Anchor Liquor",
    "lat": 27.9254816,
    "long": -82.453146,
    "gmapsCategory": "Liquor store"
  },
  {
    "type": "Liquor",
    "name": "Beverage Castle",
    "lat": 27.9835964,
    "long": -82.3734257,
    "gmapsCategory": "Convenience store"
  },
  {
    "type": "Liquor",
    "name": "Publix Liquors at Britton Plaza",
    "lat": 27.9067031,
    "long": -82.502885,
    "gmapsCategory": "Liquor store"
  },
  {
    "type": "Liquor",
    "name": "Wine on Water Bar Shop",
    "lat": 27.9445462,
    "long": -82.4500913,
    "gmapsCategory": "Wine store"
  },
  {
    "type": "Liquor",
    "name": "The Cork Room",
    "lat": 27.9264962,
    "long": -82.4530054,
    "gmapsCategory": "Wine store"
  },
  {
    "type": "Liquor",
    "name": "Last Call Liquors Tampa",
    "lat": 27.9601046,
    "long": -82.4425312,
    "gmapsCategory": "Liquor store"
  },
  {
    "type": "Liquor",
    "name": "Publix Liquors at Gandy Shopping Center",
    "lat": 27.8949353,
    "long": -82.5036574,
    "gmapsCategory": "Liquor store"
  },
  {
    "type": "Liquor",
    "name": "Walmart Wine and Liquor",
    "lat": 27.9456146,
    "long": -82.4761428,
    "gmapsCategory": "Liquor store"
  },
  {
    "type": "Liquor",
    "name": "Jug Bottle Dept ",
    "lat": 28.0035057,
    "long": -82.4592622,
    "gmapsCategory": "Wine store"
  },
  {
    "type": "Liquor",
    "name": "The Wine Vault",
    "lat": 27.8939525,
    "long": -82.5119891,
    "gmapsCategory": "Liquor store"
  },
  {
    "type": "Liquor",
    "name": "The Hub Bar",
    "lat": 27.9505663,
    "long": -82.4590019,
    "gmapsCategory": "Liquor store"
  },
  {
    "type": "Liquor",
    "name": "Duckweed Urban Grocery",
    "lat": 27.9506656,
    "long": -82.4600003,
    "gmapsCategory": "Liquor store"
  },
  {
    "type": "Liquor",
    "name": "Publix Liquors at Gandy Commons",
    "lat": 27.8948042,
    "long": -82.5163586,
    "gmapsCategory": "Liquor store"
  },
  {
    "type": "Liquor",
    "name": "Duckweed Urban Grocery Liquors",
    "lat": 27.9480849,
    "long": -82.4464168,
    "gmapsCategory": "Liquor store"
  },
  {
    "type": "Liquor",
    "name": "The Cellar Wine Spirits Seminole Hard Rock Hotel Casino ",
    "lat": 27.9934677,
    "long": -82.3722448,
    "gmapsCategory": "Liquor store"
  },
  {
    "type": "Liquor",
    "name": "Quik Pick Liquor Store",
    "lat": 28.0102802,
    "long": -82.4840351,
    "gmapsCategory": "Liquor store"
  },
  {
    "type": "Liquor",
    "name": "WINE LIQUORS ",
    "lat": 27.9393069,
    "long": -82.3673179,
    "gmapsCategory": "Liquor store"
  },
  {
    "type": "Liquor",
    "name": "The Corner Mart Kitchen Wine Market",
    "lat": 27.9150911,
    "long": -82.5263313,
    "gmapsCategory": "Liquor store"
  },
  {
    "type": "Liquor",
    "name": "Touchdown Corner Store Smoke Shop",
    "lat": 27.995581,
    "long": -82.492323,
    "gmapsCategory": "Convenience store"
  },
  {
    "type": "Liquor",
    "name": "The Pantry Market Wine",
    "lat": 27.9443714,
    "long": -82.4654595,
    "gmapsCategory": "Convenience store"
  },
  {
    "type": "Liquor",
    "name": "Grey Goose Vodka",
    "lat": 27.9710733,
    "long": -82.4592997,
    "gmapsCategory": "Liquor store"
  },
  {
    "type": "Liquor",
    "name": "Liquor Depot Armenia",
    "lat": 28.0117309,
    "long": -82.4844541,
    "gmapsCategory": "Liquor store"
  },
  {
    "type": "Liquor",
    "name": "Sakaya Sake Wine",
    "lat": 27.8932858,
    "long": -82.4906526,
    "gmapsCategory": "Wine store"
  },
  {
    "type": "Liquor",
    "name": "Vintage Wine Cellars",
    "lat": 27.9367643,
    "long": -82.5029798,
    "gmapsCategory": "Wine store"
  },
  {
    "type": "Liquor",
    "name": "Amore Liquors",
    "lat": 28.0113576,
    "long": -82.4857296,
    "gmapsCategory": "Liquor store"
  },
  {
    "type": "Liquor",
    "name": "Liquor",
    "lat": 27.9955261,
    "long": -82.4790393,
    "gmapsCategory": "Liquor store"
  },
  {
    "type": "Liquor",
    "name": "Ybor City Society Wine Bar",
    "lat": 27.9604645,
    "long": -82.441678,
    "gmapsCategory": "Wine bar"
  },
  {
    "type": "Liquor",
    "name": "The Island shoppe",
    "lat": 27.9388131,
    "long": -82.4516317,
    "gmapsCategory": "Convenience store"
  },
  {
    "type": "Liquor",
    "name": "Publix Super Market at Water Street Tampa",
    "lat": 27.9432913,
    "long": -82.4501598,
    "gmapsCategory": "Grocery store"
  },
  {
    "type": "Liquor",
    "name": " Eleven",
    "lat": 27.9956387,
    "long": -82.3941271,
    "gmapsCategory": "Convenience store"
  },
  {
    "type": "Liquor",
    "name": "STOP N PICK",
    "lat": 27.9892226,
    "long": -82.5130745,
    "gmapsCategory": "Convenience store"
  },
  {
    "type": "Liquor",
    "name": "Publix Super Market at Westshore",
    "lat": 27.9442769,
    "long": -82.5266511,
    "gmapsCategory": "Supermarket"
  },
  {
    "type": "Liquor",
    "name": "Time For Wine",
    "lat": 27.9873605,
    "long": -82.3974611,
    "gmapsCategory": "Wine store"
  },
  {
    "type": "Liquor",
    "name": "Chateau Cellars",
    "lat": 27.9621955,
    "long": -82.4346453,
    "gmapsCategory": "Wine bar"
  },
  {
    "type": "Liquor",
    "name": "Alpine Liquors",
    "lat": 28.0164129,
    "long": -82.4510259,
    "gmapsCategory": "Liquor store"
  },
  {
    "type": "Liquor",
    "name": "Duckweed Urban Grocery Liquor Store Westshore",
    "lat": 27.8898371,
    "long": -82.5292268,
    "gmapsCategory": "Liquor store"
  },
  {
    "type": "Liquor",
    "name": "Metro Market Ybor",
    "lat": 27.9625943,
    "long": -82.438137,
    "gmapsCategory": "Convenience store"
  },
  {
    "type": "Liquor",
    "name": "Publix Super Market at Hillsboro Plaza",
    "lat": 27.9946984,
    "long": -82.487377,
    "gmapsCategory": "Supermarket"
  },
  {
    "type": "Liquor",
    "name": "Cru Cellars Wine Bar",
    "lat": 27.922753,
    "long": -82.493402,
    "gmapsCategory": "Wine bar"
  },
  {
    "type": "Liquor",
    "name": "REBEL Convenience Stores",
    "lat": 27.9516857,
    "long": -82.4007131,
    "gmapsCategory": "Convenience store"
  },
  {
    "type": "Liquor",
    "name": "TampaDutyFree",
    "lat": 27.9794343,
    "long": -82.5380526,
    "gmapsCategory": "Duty free store"
  },
  {
    "type": "Liquor",
    "name": " Eleven",
    "lat": 27.9965463,
    "long": -82.4505856,
    "gmapsCategory": "Convenience store"
  },
  {
    "type": "Liquor",
    "name": " K Express ",
    "lat": 27.9726473,
    "long": -82.451,
    "gmapsCategory": ""
  },
  {
    "type": "Liquor",
    "name": "Coppertail Brewing Co ",
    "lat": 27.9562878,
    "long": -82.430219,
    "gmapsCategory": ""
  },
  {
    "type": "Liquor",
    "name": " Eleven",
    "lat": 27.9334773,
    "long": -82.4832923,
    "gmapsCategory": "Convenience store"
  },
  {
    "type": "Liquor",
    "name": "Henderson Bull Mart Smoke Shop",
    "lat": 27.94059,
    "long": -82.4985697,
    "gmapsCategory": "Convenience store"
  },
  {
    "type": "Liquor",
    "name": "Publix Super Market at West River",
    "lat": 27.9571615,
    "long": -82.4685572,
    "gmapsCategory": "Supermarket"
  },
  {
    "type": "Liquor",
    "name": "Thorntons",
    "lat": 27.995531,
    "long": -82.483783,
    "gmapsCategory": "Liquor store"
  },
  {
    "type": "Liquor",
    "name": "Publix Super Market at Gandy Shopping Center",
    "lat": 27.8948936,
    "long": -82.5030975,
    "gmapsCategory": "Supermarket"
  },
  {
    "type": "Liquor",
    "name": "Publix Super Market at Channel Club",
    "lat": 27.9518429,
    "long": -82.448561,
    "gmapsCategory": "Supermarket"
  },
  {
    "type": "Liquor",
    "name": "The Pint and Brew",
    "lat": 27.9462511,
    "long": -82.4584168,
    "gmapsCategory": ""
  },
  {
    "type": "Liquor",
    "name": " Eleven",
    "lat": 27.9966983,
    "long": -82.5232772,
    "gmapsCategory": "Convenience store"
  },
  {
    "type": "Liquor",
    "name": "Latin American SuperMarket",
    "lat": 27.9409311,
    "long": -82.3724777,
    "gmapsCategory": "Supermarket"
  },
  {
    "type": "Liquor",
    "name": " Eleven",
    "lat": 27.9407528,
    "long": -82.4937522,
    "gmapsCategory": "Convenience store"
  },
  {
    "type": "Liquor",
    "name": "Lee s Grocery",
    "lat": 27.9646778,
    "long": -82.4554714,
    "gmapsCategory": "Lee's Grocery"
  },
  {
    "type": "Liquor",
    "name": "Pour House at Grand Central",
    "lat": 27.9512124,
    "long": -82.4475215,
    "gmapsCategory": "Bar"
  },
  {
    "type": "Liquor",
    "name": " Eleven",
    "lat": 27.9808876,
    "long": -82.4851662,
    "gmapsCategory": "Convenience store"
  },
  {
    "type": "Liquor",
    "name": " Eleven",
    "lat": 27.9426134,
    "long": -82.4013045,
    "gmapsCategory": "Convenience store"
  },
  {
    "type": "Liquor",
    "name": " Eleven",
    "lat": 27.981681,
    "long": -82.4530458,
    "gmapsCategory": "Convenience store"
  },
  {
    "type": "Liquor",
    "name": " Eleven",
    "lat": 27.9260151,
    "long": -82.4527122,
    "gmapsCategory": "Convenience store"
  },
  {
    "type": "Liquor",
    "name": " Eleven",
    "lat": 27.90837,
    "long": -82.5066803,
    "gmapsCategory": "Convenience store"
  },
  {
    "type": "Liquor",
    "name": "Publix Super Market on Bayshore",
    "lat": 27.9422049,
    "long": -82.4605317,
    "gmapsCategory": "Supermarket"
  },
  {
    "type": "Liquor",
    "name": "Publix Super Market at Gandy Commons",
    "lat": 27.894706,
    "long": -82.5165641,
    "gmapsCategory": "Supermarket"
  },
  {
    "type": "Liquor",
    "name": "Gasparilla Distillery Cocktail Bar",
    "lat": 27.9583122,
    "long": -82.4352991,
    "gmapsCategory": "Liquor store"
  },
  {
    "type": "Liquor",
    "name": "Publix Super Market at Dale Mabry Shopping Center",
    "lat": 27.9307899,
    "long": -82.5072737,
    "gmapsCategory": "Supermarket"
  },
  {
    "type": "Liquor",
    "name": "Publix Super Market at Hyde Park",
    "lat": 27.9415043,
    "long": -82.4845662,
    "gmapsCategory": "Supermarket"
  },
  {
    "type": "Liquor",
    "name": " Eleven",
    "lat": 27.8941356,
    "long": -82.4940931,
    "gmapsCategory": "Convenience store"
  },
  {
    "type": "Liquor",
    "name": " Eleven",
    "lat": 27.9590445,
    "long": -82.5061938,
    "gmapsCategory": "Convenience store"
  },
  {
    "type": "Liquor",
    "name": " Eleven",
    "lat": 27.9967304,
    "long": -82.4882656,
    "gmapsCategory": "Convenience store"
  },
  {
    "type": "Liquor",
    "name": "Jet In Jet Out",
    "lat": 27.8794485,
    "long": -82.5069046,
    "gmapsCategory": "Liquor store"
  },
  {
    "type": "Liquor",
    "name": " Eleven",
    "lat": 27.8937533,
    "long": -82.5258766,
    "gmapsCategory": "Convenience store"
  },
  {
    "type": "Liquor",
    "name": " Eleven",
    "lat": 27.9665335,
    "long": -82.5011517,
    "gmapsCategory": "Convenience store"
  },
  {
    "type": "Liquor",
    "name": " Eleven",
    "lat": 27.9527891,
    "long": -82.5313181,
    "gmapsCategory": "Convenience store"
  },
  {
    "type": "Liquor",
    "name": "Publix Super Market on N Nebraska Ave",
    "lat": 28.0021444,
    "long": -82.4505619,
    "gmapsCategory": "Supermarket"
  },
  {
    "type": "Liquor",
    "name": "Brahman Liquor, Smoke Vape",
    "lat": 27.9224747,
    "long": -82.3507221,
    "gmapsCategory": "Liquor store"
  },
  {
    "type": "Liquor",
    "name": "Publix Super Market at Britton Plaza",
    "lat": 27.9071289,
    "long": -82.502558,
    "gmapsCategory": "Supermarket"
  },
  {
    "type": "Liquor",
    "name": " Eleven",
    "lat": 27.9414947,
    "long": -82.3693346,
    "gmapsCategory": "Convenience store"
  },
  {
    "type": "Liquor",
    "name": " Eleven",
    "lat": 27.9601842,
    "long": -82.4418116,
    "gmapsCategory": "Convenience store"
  },
  {
    "type": "Liquor",
    "name": "Enjoy Liquors Florida Ave",
    "lat": 28.022577,
    "long": -82.459957,
    "gmapsCategory": "Liquor store"
  },
  {
    "type": "Liquor",
    "name": "Whiskey Willy s",
    "lat": 27.996214,
    "long": -82.571691,
    "gmapsCategory": "Liquor store"
  },
  {
    "type": "Liquor",
    "name": "Mercedes Liquor Store",
    "lat": 28.025827,
    "long": -82.513557,
    "gmapsCategory": "Liquor store"
  },
  {
    "type": "Liquor",
    "name": "Liquor Depot",
    "lat": 28.0245087,
    "long": -82.5607554,
    "gmapsCategory": "Liquor store"
  },
  {
    "type": "Liquor",
    "name": "Whole Foods Market",
    "lat": 27.9528728,
    "long": -82.5048529,
    "gmapsCategory": "Grocery store"
  },
  {
    "type": "Liquor",
    "name": "Trader Joe s",
    "lat": 27.9372655,
    "long": -82.506331,
    "gmapsCategory": "Liquor store"
  },
  {
    "type": "Liquor",
    "name": "Total Wine More",
    "lat": 27.9213464,
    "long": -82.3256974,
    "gmapsCategory": "Liquor store"
  },
  {
    "type": "Liquor",
    "name": "Liquor Store",
    "lat": 27.8794901,
    "long": -82.5068649,
    "gmapsCategory": "Store"
  },
  {
    "type": "Liquor",
    "name": " Eleven",
    "lat": 27.9222226,
    "long": -82.3692264,
    "gmapsCategory": "Convenience store"
  },
  {
    "type": "Liquor",
    "name": "Gaspar s Liquor Shoppe",
    "lat": 28.0274769,
    "long": -82.3939682,
    "gmapsCategory": "Liquor store"
  },
  {
    "type": "Liquor",
    "name": "Star Liquor Pavilion",
    "lat": 27.91357,
    "long": -82.349957,
    "gmapsCategory": "Liquor store"
  },
  {
    "type": "Liquor",
    "name": "Party Liquors Fowler Ave",
    "lat": 28.053714,
    "long": -82.33578,
    "gmapsCategory": "Liquor store"
  },
  {
    "type": "Liquor",
    "name": "Beverage Island",
    "lat": 27.9981838,
    "long": -82.3192176,
    "gmapsCategory": "Liquor store"
  },
  {
    "type": "Liquor",
    "name": "Winn Dixie Wine Spirits",
    "lat": 27.9801776,
    "long": -82.288447,
    "gmapsCategory": "Liquor store"
  },
  {
    "type": "Liquor",
    "name": "Art s Lounge",
    "lat": 27.9987651,
    "long": -82.3201357,
    "gmapsCategory": "Liquor store"
  },
  {
    "type": "Liquor",
    "name": "Liquors",
    "lat": 27.9832066,
    "long": -82.2992066,
    "gmapsCategory": "Liquor store"
  },
  {
    "type": "Liquor",
    "name": " Eleven",
    "lat": 28.0218352,
    "long": -82.2438994,
    "gmapsCategory": "Convenience store"
  },
  {
    "type": "Liquor",
    "name": "Winn Dixie Wine Spirits",
    "lat": 27.9830933,
    "long": -82.308541,
    "gmapsCategory": "Liquor store"
  },
  {
    "type": "Liquor",
    "name": "Publix Liquors at Kingsway Crossing",
    "lat": 27.9586806,
    "long": -82.2792272,
    "gmapsCategory": "Liquor store"
  },
  {
    "type": "Liquor",
    "name": "Sri Fine Wine Spirits",
    "lat": 27.8945417,
    "long": -82.3302121,
    "gmapsCategory": "Liquor store"
  },
  {
    "type": "Liquor",
    "name": "Party Liquors Riverview",
    "lat": 27.8580694,
    "long": -82.3251405,
    "gmapsCategory": "Liquor store"
  },
  {
    "type": "Liquor",
    "name": "Star Liquor Big Bend Road",
    "lat": 27.7928238,
    "long": -82.3327123,
    "gmapsCategory": "Liquor store"
  },
  {
    "type": "Liquor",
    "name": "Winthrop Liquors Inc",
    "lat": 27.89169,
    "long": -82.31724,
    "gmapsCategory": "Liquor store"
  },
  {
    "type": "Liquor",
    "name": "Enjoy Liquors Riverview NOW OPEN",
    "lat": 27.8451325,
    "long": -82.3277599,
    "gmapsCategory": "Liquor store"
  },
  {
    "type": "Liquor",
    "name": "Winn Dixie Wine Spirits",
    "lat": 27.7904527,
    "long": -82.3323624,
    "gmapsCategory": "Liquor store"
  },
  {
    "type": "Liquor",
    "name": "Best Buy Liquors",
    "lat": 27.8916157,
    "long": -82.2852913,
    "gmapsCategory": "Liquor store"
  },
  {
    "type": "Liquor",
    "name": "LIQUOR CIGAR OPEN UNTIL AM ",
    "lat": 27.854707,
    "long": -82.3289243,
    "gmapsCategory": "Liquor store"
  },
  {
    "type": "Liquor",
    "name": "Liquor Cigar",
    "lat": 27.851763,
    "long": -82.268047,
    "gmapsCategory": "Liquor store"
  },
  {
    "type": "Liquor",
    "name": "Winn Dixie Wine Spirits",
    "lat": 27.8807592,
    "long": -82.3282623,
    "gmapsCategory": "Liquor store"
  },
  {
    "type": "Liquor",
    "name": "KENNY S LIQUOR",
    "lat": 27.8522774,
    "long": -82.3037217,
    "gmapsCategory": "Liquor store"
  },
  {
    "type": "Liquor",
    "name": "Valrico Liquors",
    "lat": 27.8926155,
    "long": -82.241968,
    "gmapsCategory": "Liquor store"
  },
  {
    "type": "Liquor",
    "name": "Publix Liquors at Alafia Commons",
    "lat": 27.852927,
    "long": -82.257,
    "gmapsCategory": "Liquor store"
  },
  {
    "type": "Liquor",
    "name": "Fine Wine Craft Beer at Zoom Zoom",
    "lat": 27.8549178,
    "long": -82.3396469,
    "gmapsCategory": "Wine store"
  },
  {
    "type": "Liquor",
    "name": "Twilight Zone Lounge",
    "lat": 27.9276407,
    "long": -82.0556404,
    "gmapsCategory": "Liquor store"
  },
  {
    "type": "Liquor",
    "name": "Publix Liquors at Walden Woods",
    "lat": 27.9914114,
    "long": -82.1200902,
    "gmapsCategory": "Liquor store"
  },
  {
    "type": "Liquor",
    "name": "Winn Dixie Wine Spirits",
    "lat": 27.9872076,
    "long": -82.1231468,
    "gmapsCategory": "Liquor store"
  },
  {
    "type": "Liquor",
    "name": "Walmart Wine and Liquor",
    "lat": 27.9858988,
    "long": -82.1188919,
    "gmapsCategory": "Liquor store"
  },
  {
    "type": "Liquor",
    "name": "Liquor",
    "lat": 27.9274749,
    "long": -82.0555803,
    "gmapsCategory": "Liquor store"
  },
  {
    "type": "Liquor",
    "name": " Eleven",
    "lat": 27.9885254,
    "long": -82.122433,
    "gmapsCategory": "Convenience store"
  },
  {
    "type": "Liquor",
    "name": "Publix Super Market at Walden Woods",
    "lat": 27.9908609,
    "long": -82.1198799,
    "gmapsCategory": "Supermarket"
  },
  {
    "type": "Liquor",
    "name": "Total Wine More",
    "lat": 27.816659,
    "long": -82.755952,
    "gmapsCategory": "Liquor store"
  },
  {
    "type": "Liquor",
    "name": "ABC Fine Wine Spirits",
    "lat": 27.8046589,
    "long": -82.6380852,
    "gmapsCategory": "Liquor store"
  },
  {
    "type": "Liquor",
    "name": " st Ave Liquors",
    "lat": 27.7721456,
    "long": -82.6513213,
    "gmapsCategory": "Liquor store"
  },
  {
    "type": "Liquor",
    "name": "South Central Liquors",
    "lat": 27.768931,
    "long": -82.6797396,
    "gmapsCategory": "Liquor store"
  },
  {
    "type": "Liquor",
    "name": "Gateway Liquors",
    "lat": 27.8669544,
    "long": -82.6456327,
    "gmapsCategory": "Liquor store"
  },
  {
    "type": "Liquor",
    "name": "Winn Dixie Wine Spirits",
    "lat": 27.8295892,
    "long": -82.6484899,
    "gmapsCategory": "Liquor store"
  },
  {
    "type": "Liquor",
    "name": "Detroit Liquor",
    "lat": 27.7719033,
    "long": -82.6358652,
    "gmapsCategory": "Liquor store"
  },
  {
    "type": "Liquor",
    "name": "American Spirits Fine Wines",
    "lat": 27.768637,
    "long": -82.635748,
    "gmapsCategory": "Wine store"
  },
  {
    "type": "Liquor",
    "name": "Aloha Liquor",
    "lat": 27.820614,
    "long": -82.668073,
    "gmapsCategory": "Liquor store"
  },
  {
    "type": "Liquor",
    "name": "Sunshine liquors",
    "lat": 27.8289164,
    "long": -82.6465571,
    "gmapsCategory": "Liquor store"
  },
  {
    "type": "Liquor",
    "name": "Publix Liquors at th Street Station",
    "lat": 27.805887,
    "long": -82.6399934,
    "gmapsCategory": "Liquor store"
  },
  {
    "type": "Liquor",
    "name": "Grumpy Gringo Liquor",
    "lat": 27.7708008,
    "long": -82.6710644,
    "gmapsCategory": "Liquor store"
  },
  {
    "type": "Liquor",
    "name": "Hawthorne Bottle Shoppe",
    "lat": 27.771275,
    "long": -82.6731609,
    "gmapsCategory": "Bar"
  },
  {
    "type": "Liquor",
    "name": "Winn Dixie Wine Spirits",
    "lat": 27.7907555,
    "long": -82.6781809,
    "gmapsCategory": "Liquor store"
  },
  {
    "type": "Liquor",
    "name": "Publix Liquors at Gateway Mall",
    "lat": 27.8450082,
    "long": -82.6438801,
    "gmapsCategory": "Liquor store"
  },
  {
    "type": "Liquor",
    "name": "Winn Dixie Wine Spirits",
    "lat": 27.87317,
    "long": -82.64038,
    "gmapsCategory": "Liquor store"
  },
  {
    "type": "Liquor",
    "name": "Publix Liquors at Northeast Park Shopping Center",
    "lat": 27.8063655,
    "long": -82.6350076,
    "gmapsCategory": "Liquor store"
  },
  {
    "type": "Liquor",
    "name": "Crossroads Liquor Store",
    "lat": 27.8233061,
    "long": -82.6711541,
    "gmapsCategory": "Liquor store"
  },
  {
    "type": "Liquor",
    "name": "Walmart Wine and Liquor",
    "lat": 27.844679,
    "long": -82.6854346,
    "gmapsCategory": "Liquor store"
  },
  {
    "type": "Liquor",
    "name": "Publix Liquors at Carillon Town Center",
    "lat": 27.8931565,
    "long": -82.6620623,
    "gmapsCategory": "Liquor store"
  },
  {
    "type": "Liquor",
    "name": "St Pete Cellars",
    "lat": 27.7872144,
    "long": -82.6627195,
    "gmapsCategory": "Wine store"
  },
  {
    "type": "Liquor",
    "name": "Luxus Enterprises Inc",
    "lat": 27.8176396,
    "long": -82.6798285,
    "gmapsCategory": "Liquor store"
  },
  {
    "type": "Liquor",
    "name": "Neighborhood Wine Shop",
    "lat": 27.7711742,
    "long": -82.672508,
    "gmapsCategory": "Wine store"
  },
  {
    "type": "Liquor",
    "name": "Shop TRY WINE , Fine Wine Store",
    "lat": 27.770803,
    "long": -82.6336591,
    "gmapsCategory": "Wine store"
  },
  {
    "type": "Liquor",
    "name": " Eleven",
    "lat": 27.8684215,
    "long": -82.6205783,
    "gmapsCategory": "Convenience store"
  },
  {
    "type": "Liquor",
    "name": " Eleven",
    "lat": 27.7917981,
    "long": -82.6469094,
    "gmapsCategory": "Convenience store"
  },
  {
    "type": "Liquor",
    "name": " Eleven",
    "lat": 27.8241953,
    "long": -82.6798601,
    "gmapsCategory": "Convenience store"
  },
  {
    "type": "Liquor",
    "name": "Little Food Mart",
    "lat": 27.821356,
    "long": -82.675173,
    "gmapsCategory": "Convenience store"
  },
  {
    "type": "Liquor",
    "name": "B N Food Mart Inc ",
    "lat": 27.8280768,
    "long": -82.6608417,
    "gmapsCategory": "Convenience store"
  },
  {
    "type": "Liquor",
    "name": "Icon Fuel Beverage",
    "lat": 27.7668228,
    "long": -82.6708748,
    "gmapsCategory": ""
  },
  {
    "type": "Liquor",
    "name": "TRY WINE Experience, DRINK BDINE BSHOP",
    "lat": 27.7710053,
    "long": -82.6336979,
    "gmapsCategory": "Wine bar"
  },
  {
    "type": "Liquor",
    "name": "Book B Bottle",
    "lat": 27.7716656,
    "long": -82.6415552,
    "gmapsCategory": "Liquor store"
  },
  {
    "type": "Liquor",
    "name": "Adult Therapy Wine Picnic Provisions",
    "lat": 27.7796548,
    "long": -82.6404724,
    "gmapsCategory": "Wine store"
  },
  {
    "type": "Liquor",
    "name": " Eleven",
    "lat": 27.8281593,
    "long": -82.6378779,
    "gmapsCategory": "Convenience store"
  },
  {
    "type": "Liquor",
    "name": "Whizz In Market Deli",
    "lat": 27.8090479,
    "long": -82.6710754,
    "gmapsCategory": "Convenience store"
  },
  {
    "type": "Liquor",
    "name": " Eleven",
    "lat": 27.8484926,
    "long": -82.6384509,
    "gmapsCategory": "Convenience store"
  },
  {
    "type": "Liquor",
    "name": "Publix Super Market at th Street Station",
    "lat": 27.8058723,
    "long": -82.6400305,
    "gmapsCategory": "Supermarket"
  },
  {
    "type": "Liquor",
    "name": "Walgreens",
    "lat": 27.8708912,
    "long": -82.6475501,
    "gmapsCategory": "Drug store"
  },
  {
    "type": "Liquor",
    "name": " Eleven",
    "lat": 27.8771557,
    "long": -82.6397874,
    "gmapsCategory": "Convenience store"
  },
  {
    "type": "Liquor",
    "name": " Eleven",
    "lat": 27.839493,
    "long": -82.682926,
    "gmapsCategory": "Convenience store"
  },
  {
    "type": "Liquor",
    "name": " Eleven",
    "lat": 27.7990735,
    "long": -82.6552646,
    "gmapsCategory": "Convenience store"
  },
  {
    "type": "Liquor",
    "name": "The Wine Cave The Dutchman",
    "lat": 27.7743145,
    "long": -82.6388697,
    "gmapsCategory": "Wine bar"
  },
  {
    "type": "Liquor",
    "name": " Eleven",
    "lat": 27.7770097,
    "long": -82.6788899,
    "gmapsCategory": "Convenience store"
  },
  {
    "type": "Liquor",
    "name": " Eleven",
    "lat": 27.8483981,
    "long": -82.6466347,
    "gmapsCategory": "Convenience store"
  },
  {
    "type": "Liquor",
    "name": "Publix Super Market at Carillon Town Center",
    "lat": 27.8931391,
    "long": -82.6621574,
    "gmapsCategory": "Supermarket"
  },
  {
    "type": "Liquor",
    "name": "Publix Super Market at University Village",
    "lat": 27.7691019,
    "long": -82.6364002,
    "gmapsCategory": "Supermarket"
  },
  {
    "type": "Liquor",
    "name": "Publix Super Market on th Street North",
    "lat": 27.7887341,
    "long": -82.680827,
    "gmapsCategory": "Supermarket"
  },
  {
    "type": "Liquor",
    "name": "Publix Super Market at Northeast Park Shopping Center",
    "lat": 27.8064825,
    "long": -82.6350707,
    "gmapsCategory": "Supermarket"
  },
  {
    "type": "Liquor",
    "name": "RaceTrac",
    "lat": 27.7925656,
    "long": -82.6708172,
    "gmapsCategory": ""
  },
  {
    "type": "Liquor",
    "name": "RaceTrac",
    "lat": 27.8216577,
    "long": -82.6679739,
    "gmapsCategory": ""
  },
  {
    "type": "Liquor",
    "name": "Publix Super Market at Gateway Crossing",
    "lat": 27.8669998,
    "long": -82.6461592,
    "gmapsCategory": "Supermarket"
  },
  {
    "type": "Liquor",
    "name": "Publix Super Market at Central",
    "lat": 27.7707203,
    "long": -82.6442727,
    "gmapsCategory": "Supermarket"
  },
  {
    "type": "Liquor",
    "name": "CVS",
    "lat": 27.7809084,
    "long": -82.6382577,
    "gmapsCategory": "Drug store"
  },
  {
    "type": "Liquor",
    "name": "CVS",
    "lat": 27.7680821,
    "long": -82.6374777,
    "gmapsCategory": "Drug store"
  },
  {
    "type": "Liquor",
    "name": "CVS",
    "lat": 27.84552,
    "long": -82.64621,
    "gmapsCategory": "Drug store"
  },
  {
    "type": "Liquor",
    "name": "JJ s Market Deli",
    "lat": 27.86742,
    "long": -82.627541,
    "gmapsCategory": "\"The decor is unique and very nice, lots of beer and wine selection as well.\""
  },
  {
    "type": "Liquor",
    "name": "Trader Joe s",
    "lat": 27.7974016,
    "long": -82.6388275,
    "gmapsCategory": "Liquor store"
  },
  {
    "type": "Liquor",
    "name": "CVS",
    "lat": 27.7924366,
    "long": -82.6801926,
    "gmapsCategory": "Drug store"
  },
  {
    "type": "Liquor",
    "name": "Publix Super Market at Gateway Mall",
    "lat": 27.8453462,
    "long": -82.6437611,
    "gmapsCategory": "Supermarket"
  },
  {
    "type": "Liquor",
    "name": "Whole Foods Market",
    "lat": 27.8087158,
    "long": -82.6361105,
    "gmapsCategory": "Grocery store"
  },
  {
    "type": "Liquor",
    "name": "PAP Citgo",
    "lat": 27.7990409,
    "long": -82.6710477,
    "gmapsCategory": ""
  },
  {
    "type": "Liquor",
    "name": "Thorntons",
    "lat": 27.7850255,
    "long": -82.6786804,
    "gmapsCategory": "Liquor store"
  },
  {
    "type": "Liquor",
    "name": "Walgreens",
    "lat": 27.8421095,
    "long": -82.6392149,
    "gmapsCategory": "Drug store"
  },
  {
    "type": "Liquor",
    "name": "Sam s Club",
    "lat": 27.7885723,
    "long": -82.6771684,
    "gmapsCategory": "Liquor store"
  },
  {
    "type": "Liquor",
    "name": "Spirits ",
    "lat": 27.8668625,
    "long": -82.6261114,
    "gmapsCategory": "Liquor store"
  },
  {
    "type": "Liquor",
    "name": "CellarMasters Wine Bar and Bottle Shop",
    "lat": 27.7722284,
    "long": -82.6484497,
    "gmapsCategory": "Wine store"
  },
  {
    "type": "Liquor",
    "name": "Total Wine More",
    "lat": 28.021277,
    "long": -82.733049,
    "gmapsCategory": "Liquor store"
  },
  {
    "type": "Liquor",
    "name": "ABC Fine Wine Spirits",
    "lat": 28.0144094,
    "long": -82.6133684,
    "gmapsCategory": "Liquor store"
  },
  {
    "type": "Liquor",
    "name": "Bottle Rack",
    "lat": 28.0642568,
    "long": -82.5501717,
    "gmapsCategory": "Liquor store"
  },
  {
    "type": "Liquor",
    "name": " AM Liquors",
    "lat": 28.03232,
    "long": -82.646216,
    "gmapsCategory": "Liquor store"
  },
  {
    "type": "Liquor",
    "name": "Publix Liquors on W Hillsborough Ave",
    "lat": 27.99747,
    "long": -82.583832,
    "gmapsCategory": "Liquor store"
  },
  {
    "type": "Liquor",
    "name": "Tampa Liquorz",
    "lat": 28.027354,
    "long": -82.583838,
    "gmapsCategory": "Liquor store"
  },
  {
    "type": "Liquor",
    "name": "Liquor Store",
    "lat": 28.0245908,
    "long": -82.5607484,
    "gmapsCategory": "Liquor store"
  },
  {
    "type": "Liquor",
    "name": "Publix Liquors at Westgate Plaza",
    "lat": 28.0594045,
    "long": -82.5438372,
    "gmapsCategory": "Liquor store"
  },
  {
    "type": "Liquor",
    "name": "Publix Liquors at Westchase",
    "lat": 28.0568873,
    "long": -82.6244278,
    "gmapsCategory": "Liquor store"
  },
  {
    "type": "Liquor",
    "name": "Walmart Wine and Liquor",
    "lat": 28.0432404,
    "long": -82.6744034,
    "gmapsCategory": "Liquor store"
  },
  {
    "type": "Liquor",
    "name": "Walmart Wine and Liquor",
    "lat": 28.0622766,
    "long": -82.5522906,
    "gmapsCategory": "Liquor store"
  },
  {
    "type": "Liquor",
    "name": "Publix Liquors at North Bay Commerce Center",
    "lat": 28.0356693,
    "long": -82.6465556,
    "gmapsCategory": "Liquor store"
  },
  {
    "type": "Liquor",
    "name": "Walmart Wine and Liquor",
    "lat": 28.0062194,
    "long": -82.5987008,
    "gmapsCategory": "Liquor store"
  },
  {
    "type": "Liquor",
    "name": "Walmart Liquor",
    "lat": 28.062154,
    "long": -82.5530244,
    "gmapsCategory": "Liquor store"
  },
  {
    "type": "Liquor",
    "name": "Beer Beverage Town N Country",
    "lat": 27.9988967,
    "long": -82.5650334,
    "gmapsCategory": "Beer store"
  },
  {
    "type": "Liquor",
    "name": "George mart",
    "lat": 27.990648,
    "long": -82.5501703,
    "gmapsCategory": "Grocery store"
  },
  {
    "type": "Liquor",
    "name": "Quick Mart",
    "lat": 28.0255039,
    "long": -82.5752857,
    "gmapsCategory": "Convenience store"
  },
  {
    "type": "Liquor",
    "name": "Publix Super Market at North Bay Commerce Center",
    "lat": 28.0357151,
    "long": -82.6465784,
    "gmapsCategory": "Supermarket"
  },
  {
    "type": "Liquor",
    "name": " Eleven",
    "lat": 28.0420639,
    "long": -82.6718032,
    "gmapsCategory": "Convenience store"
  },
  {
    "type": "Liquor",
    "name": " Eleven",
    "lat": 27.9971011,
    "long": -82.5753219,
    "gmapsCategory": "Convenience store"
  },
  {
    "type": "Liquor",
    "name": " Eleven",
    "lat": 28.0113119,
    "long": -82.6101217,
    "gmapsCategory": "Convenience store"
  },
  {
    "type": "Liquor",
    "name": " Eleven",
    "lat": 28.034173,
    "long": -82.647985,
    "gmapsCategory": "Convenience store"
  },
  {
    "type": "Liquor",
    "name": " Eleven",
    "lat": 28.0650934,
    "long": -82.5801874,
    "gmapsCategory": "Convenience store"
  },
  {
    "type": "Liquor",
    "name": " Eleven",
    "lat": 28.0398281,
    "long": -82.5424253,
    "gmapsCategory": "Convenience store"
  },
  {
    "type": "Liquor",
    "name": " Eleven",
    "lat": 27.9987899,
    "long": -82.5836848,
    "gmapsCategory": "Convenience store"
  },
  {
    "type": "Liquor",
    "name": "RaceTrac",
    "lat": 28.0248573,
    "long": -82.5463768,
    "gmapsCategory": ""
  },
  {
    "type": "Liquor",
    "name": "RaceTrac",
    "lat": 28.0411847,
    "long": -82.5657791,
    "gmapsCategory": ""
  },
  {
    "type": "Liquor",
    "name": " Eleven",
    "lat": 28.0558319,
    "long": -82.6231886,
    "gmapsCategory": "Convenience store"
  },
  {
    "type": "Liquor",
    "name": "Cacciatore Bros",
    "lat": 28.0001029,
    "long": -82.5632865,
    "gmapsCategory": "Italian grocery store"
  },
  {
    "type": "Liquor",
    "name": "CVS",
    "lat": 27.9970965,
    "long": -82.5813827,
    "gmapsCategory": "Drug store"
  },
  {
    "type": "Liquor",
    "name": " Eleven",
    "lat": 27.98221,
    "long": -82.5509007,
    "gmapsCategory": "Convenience store"
  },
  {
    "type": "Liquor",
    "name": "RaceTrac",
    "lat": 28.0278141,
    "long": -82.6371493,
    "gmapsCategory": "\"The store is consistently clean, well-stocked, and has a great vibe.\""
  },
  {
    "type": "Liquor",
    "name": "Publix Super Market on W Hillsborough Ave",
    "lat": 27.997848,
    "long": -82.5838652,
    "gmapsCategory": "Supermarket"
  },
  {
    "type": "Liquor",
    "name": "Publix Super Market at Westgate Plaza",
    "lat": 28.059822,
    "long": -82.5439623,
    "gmapsCategory": "Supermarket"
  },
  {
    "type": "Liquor",
    "name": "BJ s Wholesale Club",
    "lat": 28.0272796,
    "long": -82.5650135,
    "gmapsCategory": "Liquor store"
  },
  {
    "type": "Liquor",
    "name": "Spanish Wine Imports",
    "lat": 28.0087386,
    "long": -82.5429541,
    "gmapsCategory": "Liquor store"
  },
  {
    "type": "Liquor",
    "name": "Bullfrog Creek Bar and Liquors",
    "lat": 27.8390529,
    "long": -82.3812434,
    "gmapsCategory": "Liquor store"
  },
  {
    "type": "Liquor",
    "name": "Publix Liquors at Belmont Shopping Center",
    "lat": 27.7694344,
    "long": -82.3366285,
    "gmapsCategory": "Liquor store"
  },
  {
    "type": "Liquor",
    "name": "Walmart Wine and Liquor",
    "lat": 27.8476806,
    "long": -82.3533537,
    "gmapsCategory": "Liquor store"
  },
  {
    "type": "Liquor",
    "name": "BALM LIQUOR and WINE Cheers Now Open",
    "lat": 27.8189839,
    "long": -82.2955072,
    "gmapsCategory": "Liquor store"
  },
  {
    "type": "Liquor",
    "name": "Publix Liquors at Rivercrest Commons Shopping Center",
    "lat": 27.83324,
    "long": -82.3267377,
    "gmapsCategory": "Liquor store"
  },
  {
    "type": "Liquor",
    "name": "Publix Liquors at Bloomingdale Square",
    "lat": 27.8911366,
    "long": -82.2705526,
    "gmapsCategory": "Liquor store"
  },
  {
    "type": "Liquor",
    "name": "Walmart Wine and Liquor",
    "lat": 27.8962221,
    "long": -82.2486164,
    "gmapsCategory": "Liquor store"
  },
  {
    "type": "Liquor",
    "name": "Publix Liquors at The Shops at Big Bend",
    "lat": 27.7906174,
    "long": -82.3737536,
    "gmapsCategory": "Liquor store"
  },
  {
    "type": "Liquor",
    "name": "Beer Wine Spirits",
    "lat": 27.8478155,
    "long": -82.3533872,
    "gmapsCategory": "Liquor store"
  },
  {
    "type": "Liquor",
    "name": "REBEL Convenience Stores",
    "lat": 27.7925642,
    "long": -82.3356552,
    "gmapsCategory": "Convenience store"
  },
  {
    "type": "Liquor",
    "name": "REBEL Convenience Stores",
    "lat": 27.8532561,
    "long": -82.3050824,
    "gmapsCategory": "Convenience store"
  },
  {
    "type": "Liquor",
    "name": "Publix Super Market at Bloomingdale Square",
    "lat": 27.8909489,
    "long": -82.2701128,
    "gmapsCategory": "Supermarket"
  },
  {
    "type": "Liquor",
    "name": "Publix Super Market at Alafia Commons",
    "lat": 27.8526655,
    "long": -82.2565512,
    "gmapsCategory": "Supermarket"
  },
  {
    "type": "Liquor",
    "name": " Eleven",
    "lat": 27.8557268,
    "long": -82.3275297,
    "gmapsCategory": "Convenience store"
  },
  {
    "type": "Liquor",
    "name": "RaceTrac",
    "lat": 27.8929767,
    "long": -82.330137,
    "gmapsCategory": "\"Such a nice and clean store full of friendly staff\""
  },
  {
    "type": "Liquor",
    "name": "Publix Super Market at Summerfield Crossings",
    "lat": 27.7936759,
    "long": -82.3331876,
    "gmapsCategory": "Supermarket"
  },
  {
    "type": "Liquor",
    "name": " Eleven",
    "lat": 27.8211185,
    "long": -82.2968782,
    "gmapsCategory": "Convenience store"
  },
  {
    "type": "Liquor",
    "name": " Eleven",
    "lat": 27.854022,
    "long": -82.3013063,
    "gmapsCategory": "Convenience store"
  },
  {
    "type": "Liquor",
    "name": "RaceTrac",
    "lat": 27.87224,
    "long": -82.3259205,
    "gmapsCategory": ""
  },
  {
    "type": "Liquor",
    "name": " Eleven",
    "lat": 27.79198,
    "long": -82.37384,
    "gmapsCategory": "Convenience store"
  },
  {
    "type": "Liquor",
    "name": " Eleven",
    "lat": 27.8531088,
    "long": -82.2687263,
    "gmapsCategory": "Convenience store"
  },
  {
    "type": "Liquor",
    "name": " Eleven",
    "lat": 27.7914912,
    "long": -82.3342422,
    "gmapsCategory": "Convenience store"
  },
  {
    "type": "Liquor",
    "name": "Publix Super Market at Rivercrest Commons Shopping Center",
    "lat": 27.8335379,
    "long": -82.3266793,
    "gmapsCategory": "Supermarket"
  },
  {
    "type": "Liquor",
    "name": "Publix Super Market at Winthrop Town Center",
    "lat": 27.8914179,
    "long": -82.3177332,
    "gmapsCategory": "Supermarket"
  },
  {
    "type": "Liquor",
    "name": " Eleven",
    "lat": 27.8059287,
    "long": -82.2890449,
    "gmapsCategory": "Convenience store"
  },
  {
    "type": "Liquor",
    "name": "RaceTrac",
    "lat": 27.8559506,
    "long": -82.3400405,
    "gmapsCategory": ""
  },
  {
    "type": "Liquor",
    "name": "Gibsonton Smoke Shop",
    "lat": 27.8456256,
    "long": -82.381165,
    "gmapsCategory": ""
  },
  {
    "type": "Liquor",
    "name": "TONIC LIQUOR, WINE, SMOKE MORE",
    "lat": 27.8149089,
    "long": -82.6996436,
    "gmapsCategory": "Liquor store"
  },
  {
    "type": "Liquor",
    "name": "Publix Liquors at Park Boulevard Plaza",
    "lat": 27.8400965,
    "long": -82.6988941,
    "gmapsCategory": "Liquor store"
  },
  {
    "type": "Liquor",
    "name": "Feather Sound Liquors",
    "lat": 27.8945787,
    "long": -82.667464,
    "gmapsCategory": "Liquor store"
  },
  {
    "type": "Liquor",
    "name": "Disston Liquor store",
    "lat": 27.8051984,
    "long": -82.6989638,
    "gmapsCategory": "Liquor store"
  },
  {
    "type": "Liquor",
    "name": "Dolphin Village Liquors",
    "lat": 27.7233848,
    "long": -82.73977,
    "gmapsCategory": "Liquor store"
  },
  {
    "type": "Liquor",
    "name": "ABC Fine Wine Spirits",
    "lat": 27.7703453,
    "long": -82.7670513,
    "gmapsCategory": "Liquor store"
  },
  {
    "type": "Liquor",
    "name": "Pappys Liquors ,Wine , Beer And More",
    "lat": 27.7353126,
    "long": -82.7472461,
    "gmapsCategory": "Liquor store"
  },
  {
    "type": "Liquor",
    "name": "Norman E s Liquors and Fine Wines",
    "lat": 27.726445,
    "long": -82.741621,
    "gmapsCategory": "Liquor store"
  },
  {
    "type": "Liquor",
    "name": "Pasadena Liquors Fine Wines",
    "lat": 27.7589107,
    "long": -82.7359127,
    "gmapsCategory": "Liquor store"
  },
  {
    "type": "Liquor",
    "name": "Publix Liquors at South Pasadena",
    "lat": 27.760513,
    "long": -82.7368565,
    "gmapsCategory": "Liquor store"
  },
  {
    "type": "Liquor",
    "name": "Winn Dixie Wine Spirits",
    "lat": 27.7591241,
    "long": -82.7340174,
    "gmapsCategory": "Liquor store"
  },
  {
    "type": "Liquor",
    "name": "Atcoast market",
    "lat": 27.7571799,
    "long": -82.7646944,
    "gmapsCategory": "Convenience store"
  },
  {
    "type": "Liquor",
    "name": "Publix Liquors on Treasure Island",
    "lat": 27.7660159,
    "long": -82.7674756,
    "gmapsCategory": "Liquor store"
  },
  {
    "type": "Liquor",
    "name": "Winn Dixie Wine Spirits",
    "lat": 27.8033851,
    "long": -82.8024368,
    "gmapsCategory": "Liquor store"
  },
  {
    "type": "Liquor",
    "name": "Zeno s Wine Shop",
    "lat": 27.7858291,
    "long": -82.7809641,
    "gmapsCategory": "Wine store"
  },
  {
    "type": "Liquor",
    "name": "Valenty s Lounge",
    "lat": 27.7588296,
    "long": -82.7357016,
    "gmapsCategory": ""
  },
  {
    "type": "Liquor",
    "name": " Eleven",
    "lat": 27.7919937,
    "long": -82.7893596,
    "gmapsCategory": "Convenience store"
  },
  {
    "type": "Liquor",
    "name": "Herban Flow Tyrone",
    "lat": 27.7907067,
    "long": -82.7343138,
    "gmapsCategory": ""
  },
  {
    "type": "Liquor",
    "name": "Walgreens",
    "lat": 27.7680727,
    "long": -82.7683011,
    "gmapsCategory": "Drug store"
  },
  {
    "type": "Liquor",
    "name": " Eleven",
    "lat": 27.7965839,
    "long": -82.754156,
    "gmapsCategory": "Convenience store"
  },
  {
    "type": "Liquor",
    "name": " Eleven",
    "lat": 27.8010666,
    "long": -82.8005448,
    "gmapsCategory": "Convenience store"
  },
  {
    "type": "Liquor",
    "name": " Eleven",
    "lat": 27.7340948,
    "long": -82.7456883,
    "gmapsCategory": "Convenience store"
  },
  {
    "type": "Liquor",
    "name": "Publix Super Market on Treasure Island",
    "lat": 27.7660074,
    "long": -82.7674599,
    "gmapsCategory": "Supermarket"
  },
  {
    "type": "Liquor",
    "name": "Walgreens",
    "lat": 27.7435785,
    "long": -82.749957,
    "gmapsCategory": "Drug store"
  },
  {
    "type": "Liquor",
    "name": " Eleven",
    "lat": 27.755448,
    "long": -82.7638097,
    "gmapsCategory": "Convenience store"
  },
  {
    "type": "Liquor",
    "name": "Kwik Stop",
    "lat": 27.77054,
    "long": -82.740206,
    "gmapsCategory": "Convenience store"
  },
  {
    "type": "Liquor",
    "name": "Publix Super Market at South Pasadena",
    "lat": 27.760173,
    "long": -82.7371757,
    "gmapsCategory": "Supermarket"
  },
  {
    "type": "Liquor",
    "name": "Island Life Pass a Grille",
    "lat": 27.689271,
    "long": -82.7361341,
    "gmapsCategory": "Variety store"
  },
  {
    "type": "Liquor",
    "name": "Winn Dixie",
    "lat": 27.7593458,
    "long": -82.7336999,
    "gmapsCategory": "Grocery store"
  },
  {
    "type": "Liquor",
    "name": "Vino Simpatico",
    "lat": 27.7631057,
    "long": -82.7343559,
    "gmapsCategory": "Wine store"
  },
  {
    "type": "Liquor",
    "name": "Johns Pass Convenience Store",
    "lat": 27.7858193,
    "long": -82.7818604,
    "gmapsCategory": "Convenience store"
  },
  {
    "type": "Liquor",
    "name": "S A Liquors",
    "lat": 27.8148732,
    "long": -82.6996892,
    "gmapsCategory": "Liquor store"
  },
  {
    "type": "Liquor",
    "name": "ABC Fine Wine Spirits",
    "lat": 27.7975455,
    "long": -82.7279345,
    "gmapsCategory": "Liquor store"
  },
  {
    "type": "Liquor",
    "name": "Publix Liquors",
    "lat": 27.8073288,
    "long": -82.7296462,
    "gmapsCategory": "Liquor store"
  },
  {
    "type": "Liquor",
    "name": "Pic Pac Liquors",
    "lat": 27.7712704,
    "long": -82.7287221,
    "gmapsCategory": "Liquor store"
  },
  {
    "type": "Liquor",
    "name": "Publix Liquors at Madeira Shopping Center",
    "lat": 27.8104971,
    "long": -82.792301,
    "gmapsCategory": "Liquor store"
  },
  {
    "type": "Liquor",
    "name": "WINE LIQUORS ",
    "lat": 27.7822419,
    "long": -82.7139014,
    "gmapsCategory": "Liquor store"
  },
  {
    "type": "Liquor",
    "name": "Fine Wine",
    "lat": 27.7712787,
    "long": -82.7288442,
    "gmapsCategory": "Liquor store"
  },
  {
    "type": "Liquor",
    "name": "Sam s Food Mart",
    "lat": 27.7711896,
    "long": -82.7245561,
    "gmapsCategory": "Convenience store"
  },
  {
    "type": "Liquor",
    "name": "Ruskin Liquors",
    "lat": 27.724035,
    "long": -82.4334451,
    "gmapsCategory": "Liquor store"
  },
  {
    "type": "Liquor",
    "name": "Publix Liquors at Southshore Village",
    "lat": 27.7376298,
    "long": -82.4298948,
    "gmapsCategory": "Liquor store"
  },
  {
    "type": "Liquor",
    "name": "Mango Jo s Bar and Liquors",
    "lat": 27.7135946,
    "long": -82.3984841,
    "gmapsCategory": "Liquor store"
  },
  {
    "type": "Liquor",
    "name": "Quik Mart",
    "lat": 27.7209969,
    "long": -82.4394408,
    "gmapsCategory": "Convenience store"
  },
  {
    "type": "Liquor",
    "name": "Fat Boys",
    "lat": 27.7234624,
    "long": -82.4333911,
    "gmapsCategory": "Convenience store"
  },
  {
    "type": "Liquor",
    "name": "ABC Fine Wine Spirits",
    "lat": 27.767008,
    "long": -82.393927,
    "gmapsCategory": "Liquor store"
  },
  {
    "type": "Liquor",
    "name": "ABC Fine Wine Spirits",
    "lat": 27.7670082,
    "long": -82.3939275,
    "gmapsCategory": "Liquor store"
  },
  {
    "type": "Liquor",
    "name": "Apollo Beach Liquors",
    "lat": 27.7706765,
    "long": -82.3928744,
    "gmapsCategory": "Liquor store"
  },
  {
    "type": "Liquor",
    "name": "Liquor Depot Bearss",
    "lat": 28.081572,
    "long": -82.432748,
    "gmapsCategory": "Liquor store"
  },
  {
    "type": "Liquor",
    "name": "ABC Fine Wine Spirits",
    "lat": 28.0806488,
    "long": -82.5056724,
    "gmapsCategory": "Liquor store"
  },
  {
    "type": "Liquor",
    "name": "Carrollwood Fine Wine Spirits",
    "lat": 28.051889,
    "long": -82.50315,
    "gmapsCategory": "Liquor store"
  },
  {
    "type": "Liquor",
    "name": "Bull Liquors Cigar",
    "lat": 28.0827441,
    "long": -82.412253,
    "gmapsCategory": "Liquor store"
  },
  {
    "type": "Liquor",
    "name": "Sunshine Liquors",
    "lat": 28.0870909,
    "long": -82.4612873,
    "gmapsCategory": "Liquor store"
  },
  {
    "type": "Liquor",
    "name": "Falls Liquor",
    "lat": 28.0877982,
    "long": -82.4042828,
    "gmapsCategory": "Liquor store"
  },
  {
    "type": "Liquor",
    "name": "Winn Dixie Wine Spirits",
    "lat": 28.0553461,
    "long": -82.4292338,
    "gmapsCategory": "Liquor store"
  },
  {
    "type": "Liquor",
    "name": "Liquor Depot Nebraska",
    "lat": 28.0347058,
    "long": -82.4509462,
    "gmapsCategory": "Liquor store"
  },
  {
    "type": "Liquor",
    "name": "Liquor Depot Florida",
    "lat": 28.0407555,
    "long": -82.4588698,
    "gmapsCategory": "Liquor store"
  },
  {
    "type": "Liquor",
    "name": "A Liquor",
    "lat": 28.0720226,
    "long": -82.42921,
    "gmapsCategory": "Liquor store"
  },
  {
    "type": "Liquor",
    "name": "Winn Dixie Wine Spirits",
    "lat": 28.0701553,
    "long": -82.4605524,
    "gmapsCategory": "Liquor store"
  },
  {
    "type": "Liquor",
    "name": "Alamo Liquor",
    "lat": 28.0708855,
    "long": -82.45141,
    "gmapsCategory": "Liquor store"
  },
  {
    "type": "Liquor",
    "name": "Bulls Liquor II",
    "lat": 28.047557,
    "long": -82.426685,
    "gmapsCategory": "Liquor store"
  },
  {
    "type": "Liquor",
    "name": "A Liquor",
    "lat": 28.0858443,
    "long": -82.5390118,
    "gmapsCategory": "Liquor store"
  },
  {
    "type": "Liquor",
    "name": "Klasic Liquor",
    "lat": 28.06886,
    "long": -82.443027,
    "gmapsCategory": "Liquor store"
  },
  {
    "type": "Liquor",
    "name": "MDP Liquor B The Drinks at Bar Grill",
    "lat": 28.126061,
    "long": -82.5008165,
    "gmapsCategory": "Liquor store"
  },
  {
    "type": "Liquor",
    "name": "Publix Liquors at The Village Center",
    "lat": 28.0672235,
    "long": -82.5064255,
    "gmapsCategory": "Liquor store"
  },
  {
    "type": "Liquor",
    "name": "Pete s Place North Liquor Store",
    "lat": 28.029636,
    "long": -82.504433,
    "gmapsCategory": "Liquor store"
  },
  {
    "type": "Liquor",
    "name": "Publix Liquors at Carrollwood Square",
    "lat": 28.0841342,
    "long": -82.5426014,
    "gmapsCategory": "Liquor store"
  },
  {
    "type": "Liquor",
    "name": "Walmart Wine and Liquor",
    "lat": 28.0321922,
    "long": -82.457976,
    "gmapsCategory": "Liquor store"
  },
  {
    "type": "Liquor",
    "name": "Jan s Wines Boos",
    "lat": 28.1292904,
    "long": -82.5035227,
    "gmapsCategory": "Liquor store"
  },
  {
    "type": "Liquor",
    "name": "PJ Sports Bar",
    "lat": 28.0295991,
    "long": -82.504319,
    "gmapsCategory": "Liquor store"
  },
  {
    "type": "Liquor",
    "name": "Walmart Wine and Liquor",
    "lat": 28.0497409,
    "long": -82.5182032,
    "gmapsCategory": "Liquor store"
  },
  {
    "type": "Liquor",
    "name": "Right Price Liquors",
    "lat": 28.0884434,
    "long": -82.5026323,
    "gmapsCategory": "Liquor store"
  },
  {
    "type": "Liquor",
    "name": "Bull Market",
    "lat": 28.0717285,
    "long": -82.4145009,
    "gmapsCategory": "Convenience store"
  },
  {
    "type": "Liquor",
    "name": "Save Mart",
    "lat": 28.024997,
    "long": -82.4693737,
    "gmapsCategory": "Convenience store"
  },
  {
    "type": "Liquor",
    "name": "Spirits",
    "lat": 28.0296445,
    "long": -82.5045347,
    "gmapsCategory": "Liquor store"
  },
  {
    "type": "Liquor",
    "name": "Value Market",
    "lat": 28.0585448,
    "long": -82.4590428,
    "gmapsCategory": "Convenience store"
  },
  {
    "type": "Liquor",
    "name": " Eleven",
    "lat": 28.0401764,
    "long": -82.480035,
    "gmapsCategory": "Convenience store"
  },
  {
    "type": "Liquor",
    "name": "Hoque N Sons Inc ",
    "lat": 28.0690475,
    "long": -82.4597899,
    "gmapsCategory": ""
  },
  {
    "type": "Liquor",
    "name": "REBEL Convenience Stores",
    "lat": 28.0321801,
    "long": -82.417719,
    "gmapsCategory": "Convenience store"
  },
  {
    "type": "Liquor",
    "name": "EZ Stop N Shop",
    "lat": 28.0237656,
    "long": -82.4509032,
    "gmapsCategory": "Convenience store"
  },
  {
    "type": "Liquor",
    "name": "Jerrys Armenia Drive Thru",
    "lat": 28.0567286,
    "long": -82.4793157,
    "gmapsCategory": "Convenience store"
  },
  {
    "type": "Liquor",
    "name": "Publix Super Market at Apex",
    "lat": 28.1064135,
    "long": -82.4593324,
    "gmapsCategory": "Supermarket"
  },
  {
    "type": "Liquor",
    "name": "exotic smoke shop kava hookah",
    "lat": 28.0947629,
    "long": -82.4615049,
    "gmapsCategory": ""
  },
  {
    "type": "Liquor",
    "name": "Max Mini Mart Tobacco Shop",
    "lat": 28.0944015,
    "long": -82.5065994,
    "gmapsCategory": ""
  },
  {
    "type": "Liquor",
    "name": " Eleven",
    "lat": 28.0699678,
    "long": -82.47515,
    "gmapsCategory": "Convenience store"
  },
  {
    "type": "Liquor",
    "name": "Gator Smoke Shop",
    "lat": 28.0816405,
    "long": -82.4328302,
    "gmapsCategory": ""
  },
  {
    "type": "Liquor",
    "name": "Thorntons",
    "lat": 28.0408057,
    "long": -82.5088227,
    "gmapsCategory": "Liquor store"
  },
  {
    "type": "Liquor",
    "name": "Foxy Creations LLC",
    "lat": 28.1006139,
    "long": -82.527018,
    "gmapsCategory": "Wine store"
  },
  {
    "type": "Liquor",
    "name": "Whole Foods Market",
    "lat": 28.0930314,
    "long": -82.5041994,
    "gmapsCategory": "Grocery store"
  },
  {
    "type": "Liquor",
    "name": "Peterbrooke Chocolatier B Gelato Tampa",
    "lat": 28.0555155,
    "long": -82.5027784,
    "gmapsCategory": "\"They have everything from custom chocolate bars to chocolate wine!\""
  },
  {
    "type": "Liquor",
    "name": " Eleven",
    "lat": 28.0249104,
    "long": -82.5003203,
    "gmapsCategory": "Convenience store"
  },
  {
    "type": "Liquor",
    "name": "Renzo s Carrollwood",
    "lat": 28.0794488,
    "long": -82.5061492,
    "gmapsCategory": ""
  },
  {
    "type": "Liquor",
    "name": "Sam s Club",
    "lat": 28.0964528,
    "long": -82.5005732,
    "gmapsCategory": "Liquor store"
  },
  {
    "type": "Liquor",
    "name": "Fantasy liquor",
    "lat": 28.0329469,
    "long": -82.4268145,
    "gmapsCategory": "Liquor store"
  },
  {
    "type": "Liquor",
    "name": "RaceTrac",
    "lat": 28.087393,
    "long": -82.458112,
    "gmapsCategory": ""
  },
  {
    "type": "Liquor",
    "name": "Publix Super Market at Carrollwood Square",
    "lat": 28.0842972,
    "long": -82.5430643,
    "gmapsCategory": "Supermarket"
  },
  {
    "type": "Liquor",
    "name": "Winn Dixie",
    "lat": 28.0704234,
    "long": -82.4604161,
    "gmapsCategory": "Grocery store"
  },
  {
    "type": "Liquor",
    "name": "Publix Super Market at Northgate Square",
    "lat": 28.1295163,
    "long": -82.503935,
    "gmapsCategory": "Supermarket"
  },
  {
    "type": "Liquor",
    "name": "Publix Super Market at Carrollwood Shopping Center",
    "lat": 28.0408451,
    "long": -82.5037575,
    "gmapsCategory": "Supermarket"
  },
  {
    "type": "Liquor",
    "name": "Super M Smoke Shop",
    "lat": 28.0696183,
    "long": -82.4584539,
    "gmapsCategory": ""
  },
  {
    "type": "Liquor",
    "name": "Publix Super Market at The Village Center",
    "lat": 28.0669614,
    "long": -82.5068035,
    "gmapsCategory": "Supermarket"
  },
  {
    "type": "Liquor",
    "name": "Publix Super Market at USF",
    "lat": 28.0684098,
    "long": -82.4119202,
    "gmapsCategory": "Supermarket"
  },
  {
    "type": "Liquor",
    "name": "Publix Super Market at North Pointe Plaza",
    "lat": 28.0873152,
    "long": -82.502563,
    "gmapsCategory": "Supermarket"
  },
  {
    "type": "Liquor",
    "name": "Mr Dunderbak s Restaurant and Brewery",
    "lat": 28.083089,
    "long": -82.411907,
    "gmapsCategory": "Brewpub"
  },
  {
    "type": "Liquor",
    "name": "Walgreens",
    "lat": 28.065941,
    "long": -82.5058956,
    "gmapsCategory": "Drug store"
  },
  {
    "type": "Liquor",
    "name": "CVS",
    "lat": 28.0539499,
    "long": -82.4267697,
    "gmapsCategory": "Drug store"
  },
  {
    "type": "Liquor",
    "name": "CVS",
    "lat": 28.0886017,
    "long": -82.4670482,
    "gmapsCategory": "Drug store"
  },
  {
    "type": "Liquor",
    "name": "Race Trac Fowler",
    "lat": 28.0550867,
    "long": -82.4350772,
    "gmapsCategory": ""
  },
  {
    "type": "Liquor",
    "name": "Walgreens",
    "lat": 28.0687758,
    "long": -82.4669194,
    "gmapsCategory": "Drug store"
  },
  {
    "type": "Liquor",
    "name": "Walgreens",
    "lat": 28.0697398,
    "long": -82.4267798,
    "gmapsCategory": "Drug store"
  },
  {
    "type": "Liquor",
    "name": "ABC Fine Wine Spirits",
    "lat": 27.9867578,
    "long": -81.9592919,
    "gmapsCategory": "Liquor store"
  },
  {
    "type": "Liquor",
    "name": "Lakeland liquor wine",
    "lat": 28.0269565,
    "long": -81.9767913,
    "gmapsCategory": "Store"
  },
  {
    "type": "Liquor",
    "name": "Grapevine Fine Wine Spirits",
    "lat": 27.9978917,
    "long": -81.9603427,
    "gmapsCategory": "Liquor store"
  },
  {
    "type": "Liquor",
    "name": "Margin Free Liquors",
    "lat": 28.042931,
    "long": -81.9885615,
    "gmapsCategory": "Liquor store"
  },
  {
    "type": "Liquor",
    "name": "XYZ Liquor Store ",
    "lat": 28.0269672,
    "long": -81.9764896,
    "gmapsCategory": "Liquor store"
  },
  {
    "type": "Liquor",
    "name": "Avaneesh Smoke Shop Liquor",
    "lat": 28.0110122,
    "long": -81.9318419,
    "gmapsCategory": "Liquor store"
  },
  {
    "type": "Liquor",
    "name": "Walgreens Liqour Store",
    "lat": 27.9862658,
    "long": -81.9557376,
    "gmapsCategory": "Liquor store"
  },
  {
    "type": "Liquor",
    "name": "EVEREST LIQUOR SMOKE HUB",
    "lat": 27.9738871,
    "long": -81.9892894,
    "gmapsCategory": "Liquor store"
  },
  {
    "type": "Liquor",
    "name": "First Stop Liquor Tobacco",
    "lat": 27.9387611,
    "long": -81.9768361,
    "gmapsCategory": "Liquor store"
  },
  {
    "type": "Liquor",
    "name": "Queens Discount Beverages",
    "lat": 28.0101531,
    "long": -81.9074528,
    "gmapsCategory": "Wine store"
  },
  {
    "type": "Liquor",
    "name": "Liquor Tobacco Outlet",
    "lat": 28.0138462,
    "long": -81.915988,
    "gmapsCategory": "Liquor store"
  },
  {
    "type": "Liquor",
    "name": "Publix Liquors at Grove Park Shopping Center",
    "lat": 28.0237256,
    "long": -81.9268449,
    "gmapsCategory": "Liquor store"
  },
  {
    "type": "Liquor",
    "name": "Beverage Castle",
    "lat": 27.9743263,
    "long": -81.9781366,
    "gmapsCategory": "Convenience store"
  },
  {
    "type": "Liquor",
    "name": "Shepherd Beverage Castle",
    "lat": 27.9387871,
    "long": -81.9874338,
    "gmapsCategory": "Convenience store"
  },
  {
    "type": "Liquor",
    "name": "Liquor Tobacco",
    "lat": 28.024599,
    "long": -82.1512472,
    "gmapsCategory": "Liquor store"
  },
  {
    "type": "Liquor",
    "name": "Beverage Castle",
    "lat": 28.0187444,
    "long": -82.1113115,
    "gmapsCategory": "Convenience store"
  },
  {
    "type": "Liquor",
    "name": "Quick C SUNOCO",
    "lat": 28.0549547,
    "long": -82.1322539,
    "gmapsCategory": "Convenience store"
  },
  {
    "type": "Liquor",
    "name": "Strawberry Patch Package and Lounge",
    "lat": 28.0181781,
    "long": -82.1084627,
    "gmapsCategory": ""
  },
  {
    "type": "Liquor",
    "name": "Brandon Cross Liquors",
    "lat": 27.9430432,
    "long": -82.3366279,
    "gmapsCategory": "Liquor store"
  },
  {
    "type": "Liquor",
    "name": "Star Liquor BRANDON",
    "lat": 27.9371921,
    "long": -82.2990664,
    "gmapsCategory": "Liquor store"
  },
  {
    "type": "Liquor",
    "name": "ABC Fine Wine Spirits",
    "lat": 27.9363339,
    "long": -82.2640357,
    "gmapsCategory": "Liquor store"
  },
  {
    "type": "Liquor",
    "name": "Walmart Wine and Liquor",
    "lat": 27.9400016,
    "long": -82.2647712,
    "gmapsCategory": "Liquor store"
  },
  {
    "type": "Liquor",
    "name": "Winn Dixie Wine Spirits",
    "lat": 28.05345,
    "long": -82.33468,
    "gmapsCategory": "Liquor store"
  },
  {
    "type": "Liquor",
    "name": "Beer Cave",
    "lat": 27.9371998,
    "long": -82.2522417,
    "gmapsCategory": "Liquor store"
  },
  {
    "type": "Liquor",
    "name": "Thorntons",
    "lat": 27.9372468,
    "long": -82.2805541,
    "gmapsCategory": "Liquor store"
  },
  {
    "type": "Liquor",
    "name": "Winn Dixie Wine Spirits",
    "lat": 27.9367037,
    "long": -82.2425305,
    "gmapsCategory": "Liquor store"
  },
  {
    "type": "Liquor",
    "name": "Publix Liquors at Valrico Commons",
    "lat": 27.9365856,
    "long": -82.2533628,
    "gmapsCategory": "Liquor store"
  },
  {
    "type": "Liquor",
    "name": "Josephine s Italian Market",
    "lat": 27.9382244,
    "long": -82.2949415,
    "gmapsCategory": "Italian grocery store"
  },
  {
    "type": "Liquor",
    "name": "Sam s Club",
    "lat": 27.9348404,
    "long": -82.3163007,
    "gmapsCategory": "Liquor store"
  },
  {
    "type": "Liquor",
    "name": "Winn Dixie",
    "lat": 27.9796942,
    "long": -82.2878939,
    "gmapsCategory": "Grocery store"
  },
  {
    "type": "Liquor",
    "name": "Moon Mountain",
    "lat": 27.9348492,
    "long": -82.2942799,
    "gmapsCategory": ""
  },
  {
    "type": "Liquor",
    "name": " Eleven",
    "lat": 27.9407534,
    "long": -82.3360382,
    "gmapsCategory": "Convenience store"
  },
  {
    "type": "Liquor",
    "name": " Eleven",
    "lat": 27.9380942,
    "long": -82.2941383,
    "gmapsCategory": "Convenience store"
  },
  {
    "type": "Liquor",
    "name": "Winn Dixie",
    "lat": 27.9830015,
    "long": -82.3085631,
    "gmapsCategory": "Grocery store"
  },
  {
    "type": "Liquor",
    "name": " Eleven",
    "lat": 27.9820872,
    "long": -82.2853469,
    "gmapsCategory": "Convenience store"
  },
  {
    "type": "Liquor",
    "name": "CVS",
    "lat": 27.9371055,
    "long": -82.2944128,
    "gmapsCategory": "Drug store"
  },
  {
    "type": "Liquor",
    "name": "Publix Super Market at Kingsway Crossing",
    "lat": 27.9586586,
    "long": -82.2792265,
    "gmapsCategory": "Supermarket"
  },
  {
    "type": "Liquor",
    "name": "Publix Super Market at Valrico Commons",
    "lat": 27.9364117,
    "long": -82.2537924,
    "gmapsCategory": "Supermarket"
  },
  {
    "type": "Liquor",
    "name": "Publix Super Market at Mango Square",
    "lat": 27.9828063,
    "long": -82.2989745,
    "gmapsCategory": "Supermarket"
  }
]